xagents/__init__.py
xagents/config.py
xagents/util.py
xagents/agent/__init__.py
xagents/agent/api.py
xagents/agent/common.py
xagents/agent/memory.py
xagents/agent/xagent.py
xagents/kb/__init__.py
xagents/kb/api.py
xagents/kb/common.py
xagents/kb/kb.py
xagents/kb/kb_file.py
xagents/kb/vector_store.py
xagents/loader/__init__.py
xagents/loader/api.py
xagents/loader/common.py
xagents/loader/csv_loader.py
xagents/loader/doc_loader.py
xagents/loader/docx_loader.py
xagents/loader/excel_loader.py
xagents/loader/json_loader.py
xagents/loader/jsonl_loader.py
xagents/loader/markdown_loader.py
xagents/loader/pdf_loader.py
xagents/loader/ppt_loader.py
xagents/loader/pptx_loader.py
xagents/loader/splitter.py
xagents/loader/structed.py
xagents/loader/utils.py
xagents/loader/xls_loader.py
xagents/model/__init__.py
xagents/model/api.py
xagents/model/common.py
xagents/model/local.py
xagents/model/openai.py
xagents/model/zhipu.py
xagents/tool/__init__.py
xagents/tool/api.py
xagents/tool/common_tool.py
xagents/tool/core.py
xagents/tool/web_search.py
xagent-240513.dist-info/LICENSE
xagent-240513.dist-info/METADATA
xagent-240513.dist-info/WHEEL
xagent-240513.dist-info/top_level.txt
xagent-240513.dist-info/zip-safe
xagent-240513.dist-info/RECORD
